torsession/__init__.py
torsession/async.py
torsession/sync.py
torsession/sync/__init__.py
torsession-0.2.7.dist-info/DESCRIPTION.rst
torsession-0.2.7.dist-info/METADATA
torsession-0.2.7.dist-info/RECORD
torsession-0.2.7.dist-info/WHEEL
torsession-0.2.7.dist-info/metadata.json
torsession-0.2.7.dist-info/top_level.txt
