Metadata-Version: 2.0
Name: torsession
Version: 0.2.7
Summary: An asynchronous session backend with mongodb for tornado.
Home-page: https://github.com/shiyanhui/torsession
Author: Lime YH.Shi
Author-email: shiyanhui66@gmail.com
License: http://www.apache.org/licenses/LICENSE-2.0
Keywords: torsession,mongo,mongodb,motor,session,backend,tornado,asynchronous
Platform: UNKNOWN
Classifier: Development Status :: 5 - Production/Stable
Classifier: Environment :: Console
Classifier: Intended Audience :: Developers
Classifier: License :: OSI Approved :: Apache Software License
Classifier: Operating System :: OS Independent
Classifier: Programming Language :: C
Classifier: Programming Language :: Python
Classifier: Topic :: Software Development
Classifier: Topic :: Software Development :: Build Tools
Classifier: Topic :: Software Development :: Compilers
Requires-Dist: motor (>=0.6.2)
Requires-Dist: tornado (>=3.0)
